citation_date/__init__.py
citation_date/decoder.py
citation_date/base/__init__.py
citation_date/base/date_day.py
citation_date/base/date_month.py
citation_date/base/date_year.py
citation_date/base/report.py
citation_date/base/us_uk.py
citation_date-0.2.1.dist-info/licenses/LICENSE
citation_date-0.2.1.dist-info/METADATA
citation_date-0.2.1.dist-info/WHEEL
citation_date-0.2.1.dist-info/top_level.txt
citation_date-0.2.1.dist-info/RECORD
