Metadata-Version: 2.4
Name: citation-date
Version: 0.2.1
Summary: Regex date formula and decoder - Philippine Supreme Court Decisions
Requires-Python: >=3.13
License-File: LICENSE
Requires-Dist: python-dateutil>=2.9.0.post0
Dynamic: license-file
